README.md
setup.py
emecAPI/__init__.py
emecAPI/emec_api.py
emecAPI/ies.py
emecAPI/settings.py
emecAPI/utils/__init__.py
emecAPI/utils/fields.py
python_emec_api.egg-info/PKG-INFO
python_emec_api.egg-info/SOURCES.txt
python_emec_api.egg-info/dependency_links.txt
python_emec_api.egg-info/requires.txt
python_emec_api.egg-info/top_level.txt