Metadata-Version: 2.1
Name: python-emec-api
Version: 0.0.2
Summary: Python module created to integrate your Python project with the EMEC API
Home-page: https://github.com/natanrmaia/python-emec-api
Author: natanrmaia
Author-email: contato@natanael.dev.br
Project-URL: Documentation, https://python-emec-api.readthedocs.io/en/latest/
Project-URL: Source, https://github.com/natanrmaia/python-emec-api
Project-URL: Bug Reports, https://github.com/natanrmaia/python-emec-api/issues
Classifier: Programming Language :: Python :: 3
Classifier: License :: OSI Approved :: MIT License
Classifier: Operating System :: OS Independent
Requires-Dist: aiohttp>=3.9.1
Requires-Dist: beautifulsoup4>=4.12.2
